{
  "sections": {
    "165286357733e364be": {
      "type": "rich-text",
      "disabled": true,
      "blocks": {
        "165286357781cee94b-0": {
          "type": "heading",
          "disabled": true,
          "settings": {
            "heading": "MEET NICK",
            "heading_size": "small"
          }
        },
        "165286357781cee94b-1": {
          "type": "text",
          "disabled": true,
          "settings": {
            "text": "<p>Share information about your brand with your customers. Describe a product, make announcements, or welcome customers to your store.<\/p>"
          }
        },
        "165286357781cee94b-2": {
          "type": "button",
          "disabled": true,
          "settings": {
            "button_label": "Button label",
            "button_link": "",
            "button_style_secondary": false
          }
        }
      },
      "block_order": [
        "165286357781cee94b-0",
        "165286357781cee94b-1",
        "165286357781cee94b-2"
      ],
      "settings": {
        "color_scheme": "accent-2",
        "full_width": true
      }
    },
    "1652863582d238a1d1": {
      "type": "rich-text",
      "blocks": {
        "16528635823e5e208c-0": {
          "type": "heading",
          "disabled": true,
          "settings": {
            "heading": "Talk about your brand",
            "heading_size": "medium"
          }
        },
        "16528635823e5e208c-1": {
          "type": "text",
          "disabled": true,
          "settings": {
            "text": "<p>Share information about your brand with your customers. Describe a product, make announcements, or welcome customers to your store.<\/p>"
          }
        },
        "16528635823e5e208c-2": {
          "type": "button",
          "disabled": true,
          "settings": {
            "button_label": "Button label",
            "button_link": "",
            "button_style_secondary": false
          }
        }
      },
      "block_order": [
        "16528635823e5e208c-0",
        "16528635823e5e208c-1",
        "16528635823e5e208c-2"
      ],
      "settings": {
        "color_scheme": "background-1",
        "full_width": true
      }
    },
    "16487166114939f9a7": {
      "type": "image-with-text-new",
      "blocks": {
        "1648716611451d6b26-0": {
          "type": "heading",
          "settings": {
            "heading": "WIE IS NICK?"
          }
        },
        "1648716611451d6b26-1": {
          "type": "text",
          "settings": {
            "text": "<p>Pair text with an image to focus on your chosen product, collection, or blog post. Add details on availability, style, or even provide a review.<\/p>"
          }
        },
        "1648716611451d6b26-2": {
          "type": "button",
          "disabled": true,
          "settings": {
            "button_label": "THE WHOLE DREAMTEAM",
            "button_link": "https:\/\/diace.be\/pages\/een-kijkje-achter-de-schermen",
            "button-color": "yellow"
          }
        }
      },
      "block_order": [
        "1648716611451d6b26-0",
        "1648716611451d6b26-1",
        "1648716611451d6b26-2"
      ],
      "settings": {
        "image": "shopify:\/\/shop_images\/Zonder_titel_Instagram-bericht_4.png",
        "img_preference": "image second",
        "text_over_img": "",
        "padd-top": false
      }
    },
    "main": {
      "type": "main-page",
      "disabled": true,
      "settings": {
      }
    },
    "1655124854570f07d6": {
      "type": "image-with-text-new",
      "blocks": {
        "1655124854accfdf75-0": {
          "type": "heading",
          "disabled": true,
          "settings": {
            "heading": "Image with text"
          }
        },
        "1655124854accfdf75-1": {
          "type": "text",
          "settings": {
            "text": "<p>Pair text with an image to focus on your chosen product, collection, or blog post. Add details on availability, style, or even provide a review.<\/p>"
          }
        },
        "1655124854accfdf75-2": {
          "type": "button",
          "settings": {
            "button_label": "MEET OUR TEAM",
            "button_link": "https:\/\/diace.be\/pages\/meet-our-team",
            "button-color": "yellow"
          }
        }
      },
      "block_order": [
        "1655124854accfdf75-0",
        "1655124854accfdf75-1",
        "1655124854accfdf75-2"
      ],
      "settings": {
        "img_preference": "image first",
        "text_over_img": "",
        "padd-top": false
      }
    },
    "16551249404c128f2f": {
      "type": "multicolumn",
      "blocks": {
        "165512493924f1dbea-0": {
          "type": "column",
          "settings": {
            "image": "shopify:\/\/shop_images\/Ontwerp_zonder_titel_41.png",
            "title": "Stefanie",
            "text": "<p>Director of today<\/p>"
          }
        },
        "165512493924f1dbea-1": {
          "type": "column",
          "settings": {
            "image": "shopify:\/\/shop_images\/Ontwerp_zonder_titel_42.png",
            "title": "Talitha",
            "text": "<p>Content creator<\/p>"
          }
        },
        "165512493924f1dbea-2": {
          "type": "column",
          "settings": {
            "image": "shopify:\/\/shop_images\/Ontwerp_zonder_titel_40.png",
            "title": "Laurien",
            "text": "<p>Product designer<\/p>"
          }
        }
      },
      "block_order": [
        "165512493924f1dbea-0",
        "165512493924f1dbea-1",
        "165512493924f1dbea-2"
      ],
      "settings": {
        "title": "MIJN COLLEGA'S",
        "image_width": "full",
        "image_ratio": "adapt",
        "column_alignment": "center",
        "background_style": "none",
        "button_label": "",
        "button_link": "",
        "swipe_on_mobile": false
      }
    }
  },
  "order": [
    "165286357733e364be",
    "1652863582d238a1d1",
    "16487166114939f9a7",
    "main",
    "1655124854570f07d6",
    "16551249404c128f2f"
  ]
}
