{
  "sections": {
    "main": {
      "type": "main-page",
      "disabled": true,
      "settings": {
      }
    },
    "16327568795ab9a08e": {
      "type": "text-with-background",
      "settings": {
        "text": "MODE - STAGE",
        "description": "Diacé is the online place-to-go voor alles wat met diabetes accessoires te maken heeft. Je kan bij ons terecht voor een ruim assortiment aan handige diabetes accessoires. Met meer dan 750 artikels brengen wij meer kleur in het leven met diabetes, op een leuke en aangename manier. Als jonge startup met internationale ambities zijn wij op zoek naar versterking. Ben jij klaar voor een nieuw avontuur? Dan ben jij misschien wel dé persoon die wij zoeken!\n<br><br>\n<strong>FUNCTIEOMSCHRIJVING<\/strong>\n<br><br>\nBen je helemaal verzot op het naaien, stikken en maken van nieuwe ontwerpen? Dan zoeken wij jou! Je komt in aanraking met verschillende stoffen, producten en ontwerpen, niets is hier te gek. Zin om je dagen te spenderen in ons naaiatelier en krijg je hier nog meer energie van? Je bent meer dan welkom!\nNaast het maken van onze producten, sta je ook in voor het maken van bestellingen. Zo zie je je zelfgemaakte product ook vertrekken naar onze klanten. Hoe cool is dat?\n<br><br>\n<strong>PROFIEL<\/strong>\n<br><br>Je bruist van enthousiasme, passie en nieuwe ideeën.<br>Je weet van aanpakken, out-of-the-box denken en gaat er met volle goesting tegenaan.<br> Je vindt het niet erg om mee orders in te pakken en te verzenden<br>Je hebt een beetje ervaring in het naaien, stikken en snijden van stof.<br><strong>AANBOD<\/strong>\n<br><br>Een leuke plek waar je creativiteit de loop kan gaan. Hier staat alles voor je klaar om het zo comfortabel mogelijk te maken. Toffe collega’s en veel koffie om wakker te blijven!",
        "show_btn": true,
        "link_text": "Terug",
        "link_url": "shopify:\/\/pages\/join-our-team",
        "btm_padding": false
      }
    },
    "1633675664df953849": {
      "type": "contact-form-plain",
      "settings": {
        "contact_text": "IS DEZE JOB OP JOUW LIJF GESCHREVEN? SOLLICITEER NU!",
        "section_padding": "padding-y-0",
        "section_margin": "margin-y-0",
        "name_label": "Naam",
        "email_label": "E-MAIL",
        "phone_label": "TELEFOONNUMMER",
        "motivation_label": "CV - MOTIVATIE",
        "message_label": "UW BERICHT",
        "sbmtbtn_label": "VERZENDEN"
      }
    },
    "163368746876cc4524": {
      "type": "section-with-divider",
      "blocks": {
        "e0aa5ea5-8405-43e9-90bf-fdbb9ea66798": {
          "type": "social",
          "settings": {
            "social_icon": "shopify:\/\/shop_images\/instagram.png",
            "social_icon_link": ""
          }
        },
        "2d7c74ba-c04f-4650-a2fb-99e1477359b5": {
          "type": "social",
          "settings": {
            "social_icon": "shopify:\/\/shop_images\/facebook.png",
            "social_icon_link": ""
          }
        },
        "48384eee-f2d3-4717-9498-c45c27016f94": {
          "type": "social",
          "settings": {
            "social_icon": "shopify:\/\/shop_images\/instagram.png",
            "social_icon_link": ""
          }
        },
        "2050f2ee-5627-46ec-8730-1c8fa48c7409": {
          "type": "social",
          "settings": {
            "social_icon": "shopify:\/\/shop_images\/facebook.png",
            "social_icon_link": ""
          }
        }
      },
      "block_order": [
        "e0aa5ea5-8405-43e9-90bf-fdbb9ea66798",
        "2d7c74ba-c04f-4650-a2fb-99e1477359b5",
        "48384eee-f2d3-4717-9498-c45c27016f94",
        "2050f2ee-5627-46ec-8730-1c8fa48c7409"
      ],
      "settings": {
        "share_heading": "Deel deze vacature",
        "previous_heading": "Vorige vacature",
        "next_heading": "Volgende vacature",
        "share_link": "",
        "share_title": "",
        "website_url": "",
        "share_mail": ""
      }
    }
  },
  "order": [
    "main",
    "16327568795ab9a08e",
    "1633675664df953849",
    "163368746876cc4524"
  ]
}
